portbt/__init__.py
portbt/backtest_functions.py
portbt/portfolio.py
portbt/utils.py
portbt-0.1.8.dist-info/LICENSE.txt
portbt-0.1.8.dist-info/METADATA
portbt-0.1.8.dist-info/WHEEL
portbt-0.1.8.dist-info/RECORD
