Metadata-Version: 2.1
Name: portbt
Version: 0.1.8
Summary: Python library designed to make portfolio backtesting easy and intuitive
Home-page: https://github.com/renanmoretto/portbt
License: MIT
Author: renanmoretto
Author-email: himynameisrenan@outlook.com
Requires-Python: >=3.10,<4.0
Classifier: License :: OSI Approved :: MIT License
Classifier: Programming Language :: Python :: 3
Classifier: Programming Language :: Python :: 3.10
Classifier: Programming Language :: Python :: 3.11
Requires-Dist: datetime (>=4.9,<5.0)
Requires-Dist: matplotlib (>=3.6.0,<4.0.0)
Requires-Dist: numpy (>=1.23.0,<2.0.0)
Requires-Dist: pandas (>=1.5.0,<2.0.0)
Project-URL: Repository, https://github.com/renanmoretto/portbt
